simpledots/__init__.py
simpledots/simpledots.py
simpledots/utils.py
simpledots-0.0.7.dist-info/LICENSE.txt
simpledots-0.0.7.dist-info/METADATA
simpledots-0.0.7.dist-info/WHEEL
simpledots-0.0.7.dist-info/top_level.txt
simpledots-0.0.7.dist-info/RECORD
