Metadata-Version: 2.1
Name: simpledots
Version: 0.0.7
Summary: Analysis package for smFISH and puncta-like images, focused on simplicity and ease of use.
Home-page: https://gitlab.com/lincdog/simpledots
Author: Lincoln Ombelets
Author-email: lombelets@caltech.edu
License: MIT
Platform: UNKNOWN
Classifier: Development Status :: 3 - Alpha
Classifier: Intended Audience :: Developers
Classifier: Programming Language :: Python :: 3
Classifier: License :: OSI Approved :: MIT License
Requires-Python: >=3.5
Requires-Dist: numpy
Requires-Dist: scipy
Requires-Dist: pandas
Requires-Dist: scikit-image (>=0.16.0)
Requires-Dist: xarray
Requires-Dist: bokeh
